{"COMA4011": ["FOTOGRAFIA BASICA ", "3"], "COMA4038": ["HISTORIA DEL CINE ", "3"], "COMA4100": ["PRACTICA SUPERVISADA EN TV", "3"], "COMA4105": ["PRACTICA SUPERVISADA RADIO", "3"], "COMA4106": ["PRACTICA SUPERVIS CINE ", "3"], "COMA4187": ["TEORIA Y CRITICA CINE ", "3"], "COMA4315": ["GUIONES ", "3"], "COMA4317": ["DISE\ufffdO GRAFICAS DIGITALES ", "3"], "COMA4341": ["PRODUCCION DE CINE I ", "3"], "COMA4342": ["PRODUCCION DE CINE II ", "3"], "COMA4351": ["PRODUCCION TELEVISION I ", "3"], "COMA4810": ["SEMINARIO EN RADIO ", "3"], "COMA4815": ["SEMINARIO EN CINE ", "3"], "COMA4991": ["SEM EN PRACTIC AUDIOVISUAL", "1"], "COPU4017": ["INTROD A LOS MEDIOS ", "3"], "COPU4045": ["SEMINARIO AVANZADO COMUNIC", "3"], "COPU4137": ["FUND REDACCION MEDIOS COMU", "3"], "COPU4355": ["TEORIAS DE LA COMUNICACION", "3"], "COPU4365": ["LEGISL MEDIOS Y DEONT INF ", "3"], "INFP4001": ["REDACCION PERIODISTICA I ", "3"], "INFP4002": ["REDACCION PERIODISTICA II ", "3"], "INFP4016": ["INTRODUCCION AL PERIODISMO", "3"], "INFP4036": ["DISE\ufffdO PERIOD MULTIMEDIA ", "3"], "INFP4059": ["PERIODISMO PARA RADIO Y TV", "3"], "INFP4109": ["PRACTICA SUPERV PERIOD ", "3"], "INFP4148": ["REDAC BASICA MEDIOS CONVER", "3"], "INFP4205": ["SEMINARIO EN COMUNICACION ", "3"], "INFP4809": ["SEMINARIO EN PERIODISMO ", "3"], "REPU4018": ["INTR A PUBLI Y REL PUBLIC ", "3"], "REPU4025": ["REDACCION PARA PUBLICIDAD ", "3"], "REPU4067": ["COMUNICACION ORAL ", "3"], "REPU4076": ["CONCEP ANUN AUDIO VID NTEC", "3"], "REPU4087": ["PLAN PRODUC EN RELAC PUBL ", "3"], "REPU4110": ["PRACT SUPER EN PUBLICIDAD ", "3"], "REPU4147": ["REDACCION RELAC PUBLICAS ", "3"], "REPU4155": ["PLANIFICACION DE MEDIOS ", "3"], "REPU4165": ["CAMPA\ufffdAS RELAC PUBLICAS ", "3"], "REPU4166": ["CAMPANAS DE PUBLICIDAD ", "3"], "REPU4807": ["SEM RELACIONES PUBLICAS ", "3"]}