{"DERE7007": ["DERECHOS REALES ", "3"], "DERE7008": ["DERECHO DE FAMILIA ", "3"], "DERE7015": ["DERECHO PENAL ", "3"], "DERE7016": ["OBLIGACIONES Y CONTRATOS ", "4"], "DERE7017": ["DER PROCESAL CIVIL ", "4"], "DERE7018": ["DERECHO CONSTITUCIONAL ", "4"], "DERE7019": ["DER PROCES PENAL ", "4"], "DERE7021": ["JURISDICCION FEDERAL ", "3"], "DERE7025": ["DERECHO Y CAMBIO SOCIAL ", "3"], "DERE7026": ["DERECHO PRUEBA,EVIDENCIA ", "3"], "DERE7027": ["CONTRATOS MERCANTILES ", "3"], "DERE7028": ["DERECHO ADMINISTRATIVO ", "4"], "DERE7029": ["DERECHO DE SUCESIONES ", "3"], "DERE7035": ["DERECHO HIPOTECARIO ", "3"], "DERE7039": ["TEORIA DEL DERECHO ", "3"], "DERE7041": ["CLINICA ASISTENCIA LEGAL ", "3"], "DERE7056": ["ENERGIA Y DERECHO ", "3"], "DERE7066": ["LA PROFESION JURIDICA ", "2"], "DERE7068": ["INVESTIG Y REDAC JURIDIC ", "2"], "DERE7085": ["ASP LEGAL TRANSAC INTERN ", "3"], "DERE7106": ["DERECHOS DE AUTOR ", "3"], "DERE7108": ["INTRODUCCION A PI ", "3"], "DERE7109": ["DERECHO DE PATENTES ", "3"], "DERE7115": ["DERE INTERNACION PUBLICO ", "3"], "DERE7209": ["DERECHO DE INMIGRACION ", "2"], "DERE7296": ["TALL PRAC TRIBS AGENCS ADM", "3"], "DERE7297": ["TALLER AVANZADO DE PRACTIC", "3"], "DERE7309": ["DERE MEDIOS COMUNICACION ", "3"], "DERE7508": ["GARANTIAS MOBILIARIAS ", "3"], "DERE7516": ["SEGUROS ", "3"], "DERE7518": ["DERECHO TRIBUTARIO ", "4"], "DERE7519": ["CONTABILIDAD Y DERECHO ", "2"], "DERE7527": ["LEGISLACION SOCIAL ", "3"], "DERE7528": ["ADMINISTRACION JUDICIAL ", "3"], "DERE7535": ["DERECHO LABORAL ", "4"], "DERE7539": ["LEGIS RECURSOS NATURALES ", "3"], "DERE7540": ["DERE AMBIENT INTERNACION ", "3"], "DERE7545": ["HIST DERE PUERTORRIQUENO ", "3"], "DERE7546": ["CONTRATOS ESPECIALES ", "3"], "DERE7547": ["DERE INTERNAC PRIVADO ", "3"], "DERE7556": ["PRACTICA NOTARIAL I ", "3"], "DERE7570": ["JURISPRUDENCIA TERAPEUTI ", "3"], "DERE7575": ["PRACT FORENSE,APELATIVA ", "2"], "DERE7585": ["ETICA,RESPONSAB PROFES ", "3"], "DERE7590": ["SEM TEMAS CORPS & SOCS ", "2"], "DERE7630": ["SEM TEMAS DERE MERCANT ", "2"], "DERE7640": ["SEM TEMAS EN HIST DERE ", "2"], "DERE7669": ["DERECHO Y LITERATURA ", "3"], "DERE7676": ["SEM TEMAS DERE AMBIENTAL ", "2"], "DERE7678": ["SEM TEMAS DERE CIVIL ", "2"], "DERE7680": ["SEM TEMAS DERE CONST ", "2"], "DERE7686": ["SEM TEMAS DERE INTERNACI ", "2"], "DERE7688": ["SEM TEMAS DERE PROC PENL ", "2"], "DERE7696": ["SEM TEMAS DERE LABORAL ", "2"], "DERE7698": ["SEM TEMAS DERE Y SOCIED ", "2"], "DERE7730": ["MET ALT RES DISPUTAS ", "2"], "DERE7741": ["MEDIACION I ", "3"], "DERE7745": ["ESTUDIO INDEPENDIENTE ", "2"], "DERE7991": ["TEMAS ESPEC DERECHO PRIV ", "3"], "DERE7992": ["INT DERE SEGURIDAD INFOR ", "2"], "DERE7993": ["TEMAS ESPEC DERECHO PRIV ", "2"], "DERE7994": ["GERENCIA DE LA PROF LEGAL ", "2"], "DERE7996": ["TEMAS ESPEC DERECHO PUBL ", "2"], "DERE7996_LAB": ["DESTREZAS LITIGIO PENAL ", "3"], "DERE7997": ["TEMAS ESPEC DERECHO PUBL ", "2"], "DERE7998": ["PRACT ADN POST SENTENCIA ", "2"], "DERE7998_LAB": ["NACIONALIDAD Y CIUDADANIA ", "3"], "DERE7999": ["DERE CONST EDUC ESPECIAL ", "2"], "DERE7999_LAB": ["TEORIA Y PRACT LITIGACION ", "3"]}