{"Horario ": ["Horario SEGUNDO SEMESTRE 2018-2019"], "COMA4011": ["FOTOGRAFIA BASICA", 3], "COMA4038": ["HISTORIA DEL CINE", 3], "COMA4100": ["PRACTICA SUPERVISADA EN TV", 3], "COMA4105": ["PRACTICA SUPERVISADA RADIO", 3], "COMA4106": ["PRACTICA SUPERVIS CINE", 3], "COMA4315": ["GUIONES", 3], "COMA4317": ["DISE\u00d1O GRAFICAS DIGITALES", 3], "COMA4341": ["PRODUCCION DE CINE I", 3], "COMA4342": ["PRODUCCION DE CINE II", 3], "COMA4351": ["PRODUCCION TELEVISION I", 3], "COMA4352": ["PRODUCCION TELEVISION II", 3], "COMA4362": ["PRODUCCION DE RADIO II", 3], "COMA4815": ["SEMINARIO EN CINE", 3], "COMA4991": ["DISEN GRAF PRODUC AUDIOVIS", 1], "COPU4017": ["INTROD A LOS MEDIOS", 3], "COPU4045": ["SEMINARIO AVANZADO COMUNIC", 3], "COPU4136": ["REDAC BASICA MEDIOS COMU", 3], "COPU4355": ["TEORIAS DE LA COMUNICACION", 3], "COPU4365": ["LEGISL MEDIOS Y DEONT INF", 3], "COPU4995": ["VIAJE ESTUD COMUNICACION", 3], "INFP4001": ["REDACCION PERIODISTICA I", 3], "INFP4002": ["REDACCION PERIODISTICA II", 3], "INFP4016": ["INTRODUCCION AL PERIODISMO", 3], "INFP4036": ["DISE\u00d1O PERIOD MULTIMEDIA", 3], "INFP4059": ["PERIODISMO PARA RADIO Y TV", 3], "INFP4097": ["PRACT SUP PERIOD RADIAL", 3], "INFP4099": ["PRACT SUP PERIODISMO TV", 3], "INFP4108": ["PRACT SUPERV FOTOPERIOD", 3], "INFP4109": ["PRACTICA SUPERV PERIOD", 3], "INFP4148": ["REDAC BASICA MEDIOS CONVER", 3], "INFP4809": ["SEMINARIO EN PERIODISMO", 3], "INFP4809_LAB": ["NOTICIARIO PARA TELEVISION", 1], "REPU4018": ["INTR A PUBLI Y REL PUBLIC", 3], "REPU4025": ["REDACCION PARA PUBLICIDAD", 3], "REPU4076": ["CONCEP ANUN AUDIO VID NTEC", 3], "REPU4087": ["PLAN PRODUC EN RELAC PUBL", 3], "REPU4107": ["PRACT SUPER RELAC PUBLIC", 3], "REPU4110": ["PRACT SUPER EN PUBLICIDAD", 3], "REPU4147": ["REDACCION RELAC PUBLICAS", 3], "REPU4155": ["PLANIFICACION DE MEDIOS", 3], "REPU4165": ["CAMPA\u00d1AS RELAC PUBLICAS", 3], "REPU4166": ["CAMPANAS DE PUBLICIDAD", 3]}